flask_celery3.py
setup.py
Flask_Celery3.egg-info/PKG-INFO
Flask_Celery3.egg-info/SOURCES.txt
Flask_Celery3.egg-info/dependency_links.txt
Flask_Celery3.egg-info/not-zip-safe
Flask_Celery3.egg-info/requires.txt
Flask_Celery3.egg-info/top_level.txt