Metadata-Version: 1.1
Name: Flask-Celery3
Version: 0.1
Summary: Add Celery3 integration to your Flask apps.
Home-page: https://github.com/jaapz/flask-celery3
Author: Jaap Broekhuizen
Author-email: jaapz.b@gmail.com
License: MIT
Platform: any
Classifier: Environment :: Web Environment
Classifier: Intended Audience :: Developers
Classifier: License :: OSI Approved :: MIT License
Classifier: Operating System :: OS Independent
Classifier: Programming Language :: Python
Classifier: Topic :: Internet :: WWW/HTTP :: Dynamic Content
Classifier: Topic :: Software Development :: Libraries :: Python Modules
